[{"id":0,"href":"/tutorialtest4/tags/OCI/","title":"OCI","parent":"Tags","content":"","description":""},{"id":1,"href":"/tutorialtest4/oci_beginner/","title":"OCI入門編","parent":"Oracle Cloud Infrastructure チュートリアル","content":"Kind: section\nLorem ipsum dolor sit amet, consectetur adipiscing elit, sed do eiusmod tempor incididunt ut labore et dolore magna aliqua. Ut enim ad minim veniam, quis nostrud exercitation ullamco laboris nisi ut aliquip ex ea commodo consequat. Duis aute irure dolor in reprehenderit in voluptate velit esse cillum dolore eu fugiat nulla pariatur. Excepteur sint occaecat cupidatat non proident, sunt in culpa qui officia deserunt mollit anim id est laborum.\n1.OKEセットアップ Lorem ipsum dolor sit amet, consectetur adipiscing elit, sed do eiusmod tempor incididunt ut labore et dolore magna aliqua. Ut enim ad minim veniam, quis nostrud exercitation ullamco laboris nisi ut aliquip ex ea commodo consequat.\n1-1 OCIダッシュボードからOKEクラスタの構築 Lorem ipsum dolor sit amet, consectetur adipiscing elit, sed do eiusmod tempor incididunt ut labore et dolore magna aliqua.\n1-2 Cloud Shellを利用してクラスタを操作 Lorem ipsum dolor sit amet, consectetur adipiscing elit, sed do eiusmod tempor incididunt ut labore et dolore magna aliqua. Ut enim ad minim veniam, quis nostrud exercitation ullamco laboris nisi ut aliquip ex ea commodo consequat. Duis aute irure dolor in reprehenderit in voluptate velit esse cillum dolore eu fugiat nulla pariatur. Excepteur sint occaecat cupidatat non proident, sunt in culpa qui officia deserunt mollit anim id est laborum.\n2.認証トークン セットアップ Lorem ipsum dolor sit amet, consectetur adipiscing elit, sed do eiusmod tempor incididunt ut labore et dolore magna aliqua. Ut enim ad minim veniam, quis nostrud exercitation ullamco laboris nisi ut aliquip ex ea commodo consequat.\n3.サンプルアプリケーション取得 Lorem ipsum dolor sit amet, consectetur adipiscing elit, sed do eiusmod tempor incididunt ut labore et dolore magna aliqua.\nh2 ehfsighu jfruisgur\n2.コード・リポジトリ Lorem ipsum dolor sit amet, consectetur adipiscing elit, sed do eiusmod tempor incididunt ut labore et dolore magna aliqua. Ut enim ad minim veniam, quis nostrud exercitation ullamco laboris nisi ut aliquip ex ea commodo consequat. Duis aute irure dolor in reprehenderit in voluptate velit esse cillum dolore eu fugiat nulla pariatur. Excepteur sint occaecat cupidatat non proident, sunt in culpa qui officia deserunt mollit anim id est laborum.\n2-1.コード・リポジトリの作成 Lorem ipsum dolor sit amet, consectetur adipiscing elit, sed do eiusmod tempor incididunt ut labore et dolore magna aliqua. Ut enim ad minim veniam, quis nostrud exercitation ullamco laboris nisi ut aliquip ex ea commodo consequat. Duis aute irure dolor in reprehenderit in voluptate velit esse cillum dolore eu fugiat nulla pariatur. Excepteur sint occaecat cupidatat non proident, sunt in culpa qui officia deserunt mollit anim id est laborum.\n2-2.クローンしたサンプルコードをプッシュ 2-2-1.クローン先情報を取得 Lorem ipsum dolor sit amet, consectetur adipiscing elit, sed do eiusmod tempor incididunt ut labore et dolore magna aliqua. Ut enim ad minim veniam, quis nostrud exercitation ullamco laboris nisi ut aliquip ex ea commodo consequat. Duis aute irure dolor in reprehenderit in voluptate velit esse cillum dolore eu fugiat nulla pariatur. Excepteur sint occaecat cupidatat non proident, sunt in culpa qui officia deserunt mollit anim id est laborum.\n2-2-2.「oci-devops-handson」リポジトリのユーザ名とパスワードの取得 Lorem ipsum dolor sit amet, consectetur adipiscing elit, sed do eiusmod tempor incididunt ut labore et dolore magna aliqua. Ut enim ad minim veniam, quis nostrud exercitation ullamco laboris nisi ut aliquip ex ea commodo consequat. Duis aute irure dolor in reprehenderit in voluptate velit esse cillum dolore eu fugiat nulla pariatur. Excepteur sint occaecat cupidatat non proident, sunt in culpa qui officia deserunt mollit anim id est laborum.\n3.アーティファクト Lorem ipsum dolor sit amet, consectetur adipiscing elit, sed do eiusmod tempor incididunt ut labore et dolore magna aliqua. Ut enim ad minim veniam, quis nostrud exercitation ullamco laboris nisi ut aliquip ex ea commodo consequat. Duis aute irure dolor in reprehenderit in voluptate velit esse cillum dolore eu fugiat nulla pariatur. Excepteur sint occaecat cupidatat non proident, sunt in culpa qui officia deserunt mollit anim id est laborum.\nfgr fgr fgr fgr fgr fgr fgr fgr fgr fgr fgr fgr fgr fgr fgr fgr fgr fgr fgr fgr fgr fgr fgr fgr fgr fgr fgr fgr fgr fgr fgr fgr fgr fgr fgr fgr fgr fgr fgr ociをはじめてみよう\n","description":"Kind: section\nLorem ipsum dolor sit amet, consectetur adipiscing elit, sed do eiusmod tempor incididunt ut labore et dolore magna aliqua. Ut enim ad minim veniam, quis nostrud exercitation ullamco laboris nisi ut aliquip ex ea commodo consequat. Duis aute irure dolor in reprehenderit in voluptate velit esse cillum dolore eu fugiat nulla pariatur. Excepteur sint occaecat cupidatat non proident, sunt in culpa qui officia deserunt mollit anim id est laborum.\n"},{"id":2,"href":"/tutorialtest4/","title":"Oracle Cloud Infrastructure チュートリアル","parent":"","content":"案１\n案２\n徳永律子が記入（2025/06/04）シナリオテスト１ 徳永律子が記入（2025/06/09）シナリオテスト１ 岡優作が記入(2025/06/09) シナリオテスト１ 岡優作が記入(2025/06/09)テスト2回目 Yusaku Okaが記入(2025/06/10)シナリオテスト6 北村海人が上書き(20250610) パターン5 うおおおお Yusaku Okaが記入(2025/06/10)シナリオテスト4 徳永律子が記入（2025/06/10）シナリオテスト2 Yusaku Okaが記入 (2025/06/10)シナリオテスト5 kitamuraが記入(2025/06/23) 自動PR作成テスト1 kitamuraが記入(2025/06/23) aaaaa2 aaaaaa bbbbbb\nチュートリアルコンテンツ一覧 ■ サポート・サービス活用編 オラクル・サポート、カスタマーサクセスサービスによりトラブル解決をご支援します。トラブル解決にできるだけ早く近づくための技術サポート（SR）を効果的に利用するポイントを解説しています。\n■ OCI入門編 OCIの入門編チュートリアルです。 OCIコンソールの基本的な操作方法やネットワーク、ストレージなどの基本的なサービスについてを学習できます。\n■ OCI応用編 OCIの応用編チュートリアルです。 LoadBalancerや証明書サービスなどをはじめとした各OCIサービスの応用的な使い方を学習できます。\n■ Oracle Database編 北村追記(20250610) パターン4-2\n・Autonomous Database編 Lorem ipsum dolor sit amet, consectetur adipiscing elit, sed do eiusmod tempor incididunt ut labore et dolore magna aliqua. Ut enim ad minim veniam, quis nostrud exercitation ullamco laboris nisi ut aliquip ex ea commodo consequat.\n・Base Database Service編 Oracle Database関連サービスのチュートリアルです。 自律型データベースサービスであるAutonomous DatabaseやBase Database Service、Exadata Database Service on Dedicated Infrastructure、Exadata Database Service on Exascale Infrastructure、AI Vector SearchなどOCIのデータベース・サービスを学習できます。\n■ MySQL Database Service編 Oracle MySQLチームが開発、管理およびサポートするOCI上で提供されるMySQL Database Serviceを学習できます。\n■ Cloud Native編 OCIで提供するCloud Native関連サービスのチュートリアルです。 マネージドのKubernetesサービスであるOKEやマネージドのFaaS(Functions as a Service)であるOracle Functionsを学習できます。\n■ コンテンツ管理編 セキュアな情報共有とインテリジェントなコンテンツ管理基盤であるOracle Content Management（OCM）を学習できます。\n■ ブロックチェーン編 オープン・ソースのHyperledger Fabric上に構築された業界をリードするマネージド・エンタープライズ・ブロックチェーン・サービスであるOracle Blockchain Platform Cloud Serviceを学習できます。\n■ インテグレーション編 アプリケーション、ビジネス・プロセス、API、およびデータを迅速にモダナイズするためのエンタープライズ連携および自動化プラットフォームであるOracle Integration Cloudを学習できます。\n■ データサイエンス/ビッグデータ編 Oracle Cloud Infrastructure(OCI)のデータサイエンス/ビッグデータ関連サービスのチュートリアルです。 Oracleが提供するマネージドの機械学習環境Data Science ServiceやマネージドのSpark環境であるOCI Data Flowを学習できます。\n■ アイデンティティ編 OCIのユーザー認証・アクセス制御を統合的に管理するIAM・IDaaSを提供するOCI Identity Domainsについて学習できるチュートリアルです。\n■ セキュリティ編 OCIにおける各種セキュリティ関連サービスについて学習できるチュートリアルです。 基本的なセキュリティ機能からデータベースのセキュリティ対策までの幅広いサービスチュートリアルをご紹介しています。\n■ 監視・管理編 OCIにおける各種運用・管理関連サービスについて学習できるチュートリアルです。\n■ OpenSearch編 OCI Search Service with OpenSearchに関して学習できます。\n■ OCI HPCチュートリアル集 OCI上にHPCシステムを構築するためのチュートリアルです。 OCIが提供するベアメタルインスタンス、GPUインスタンス、クラスタ・ネットワーク等を活用し、様々な用途のHPCシステムをリソース・マネージャ、Terraform、Ansibleを駆使して効率的に構築する方法を学習します。\n■ Oracle Cloud VMware Solution編 このページは、Oracle Cloud VMware Solution (OCVS) 関連のチュートリアル、ガイド、ブログなどへのリンク集です。\nhome 本コンテンツは、作成者が誠心誠意作成しておりますが、万が一、本ドキュメントの間違いや、不正確な記述などを見つけられた場合は、こちらからIssue登録にてご連絡ください。 ・ タグ検索ページリンク\n","description":"案１\n案２\n徳永律子が記入（2025/06/04）シナリオテスト１ 徳永律子が記入（2025/06/09）シナリオテスト１ 岡優作が記入(2025/06/09) シナリオテスト１ 岡優作が記入(2025/06/09)テスト2回目 Yusaku Okaが記入(2025/06/10)シナリオテスト6 北村海人が上書き(20250610) パターン5 うおおおお Yusaku Okaが記入(2025/06/10)シナリオテスト4 徳永律子が記入（2025/06/10）シナリオテスト2 Yusaku Okaが記入 (2025/06/10)シナリオテスト5 kitamuraが記入(2025/06/23) 自動PR作成テスト1 kitamuraが記入(2025/06/23) aaaaa2 aaaaaa bbbbbb\nチュートリアルコンテンツ一覧 ■ サポート・サービス活用編 オラクル・サポート、カスタマーサクセスサービスによりトラブル解決をご支援します。トラブル解決にできるだけ早く近づくための技術サポート（SR）を効果的に利用するポイントを解説しています。\n■ OCI入門編 OCIの入門編チュートリアルです。 OCIコンソールの基本的な操作方法やネットワーク、ストレージなどの基本的なサービスについてを学習できます。\n■ OCI応用編 OCIの応用編チュートリアルです。 LoadBalancerや証明書サービスなどをはじめとした各OCIサービスの応用的な使い方を学習できます。\n■ Oracle Database編 北村追記(20250610) パターン4-2\n・Autonomous Database編 Lorem ipsum dolor sit amet, consectetur adipiscing elit, sed do eiusmod tempor incididunt ut labore et dolore magna aliqua. Ut enim ad minim veniam, quis nostrud exercitation ullamco laboris nisi ut aliquip ex ea commodo consequat.\n"},{"id":3,"href":"/tutorialtest4/tags/","title":"Tags","parent":"Oracle Cloud Infrastructure チュートリアル","content":"","description":""},{"id":4,"href":"/tutorialtest4/oci_beginner/example/","title":"その1 - OCIコンソールにアクセスして基本を理解する","parent":"OCI入門編","content":"Kind: page\nh1 lorem ipsum aaa\n","description":"Kind: page\nh1 lorem ipsum aaa\n"},{"id":5,"href":"/tutorialtest4/proposal02/%E3%83%81%E3%83%A5%E3%83%BC%E3%83%88%E3%83%AA%E3%82%A2%E3%83%AB%EF%BC%91/","title":"チュートリアル１記事","parent":"案２","content":"Kind: page\nPath: /proposal02/チュートリアル１.md\n","description":"Kind: page\nPath: /proposal02/チュートリアル１.md\n"},{"id":6,"href":"/tutorialtest4/proposal01/%E3%83%81%E3%83%A5%E3%83%BC%E3%83%88%E3%83%AA%E3%82%A2%E3%83%AB%EF%BC%91/","title":"チュートリアル１記事 北村シナリオ1","parent":"案１","content":"Kind: page\nPath: /proposal01/チュートリアル１/_index.md\n","description":"Kind: page\nPath: /proposal01/チュートリアル１/_index.md\n"},{"id":7,"href":"/tutorialtest4/proposal02/%E3%83%81%E3%83%A5%E3%83%BC%E3%83%88%E3%83%AA%E3%82%A2%E3%83%AB%EF%BC%92/","title":"チュートリアル別記事","parent":"案２","content":"Kind: page\nPath: /proposal02/チュートリアル２.md\n","description":"Kind: page\nPath: /proposal02/チュートリアル２.md\n"},{"id":8,"href":"/tutorialtest4/proposal01/","title":"案１","parent":"Oracle Cloud Infrastructure チュートリアル","content":"Kind: section\nPath: proposal01/index.md\n岡優作編集(20250610)\nチュートリアル１ lerem ipsum dolor sit amet, consectetur adipiscing elit, sed do eiusmod tempor incididunt ut labore et dolore magna aliqua. Ut enim ad minim veniam, quis nostrud exercitation ullamco laboris nisi ut aliquip ex ea commodo consequat. Duis aute irure dolor in reprehenderit in voluptate velit esse cillum dolore eu fugiat nulla pariatur. Excepteur sint occaecat cupidatat non proident, sunt in culpa qui officia deserunt mollit anim id est laborum.\nチュートリアル別 lorem ipsum dolor sit amet, consectetur adipiscing elit, sed do eiusmod tempor incididunt ut labore et dolore magna aliqua. Ut enim ad minim veniam, quis nostrud exercitation ullamco laboris nisi ut aliquip ex ea commodo consequat. Duis aute irure dolor in reprehenderit in voluptate velit esse cillum dolore eu fugiat nulla pariatur. Excepteur sint occaecat cupidatat non proident, sunt in culpa qui officia deserunt mollit anim id est laborum.\n","description":"Kind: section\nPath: proposal01/index.md\n岡優作編集(20250610)\nチュートリアル１ lerem ipsum dolor sit amet, consectetur adipiscing elit, sed do eiusmod tempor incididunt ut labore et dolore magna aliqua. Ut enim ad minim veniam, quis nostrud exercitation ullamco laboris nisi ut aliquip ex ea commodo consequat. Duis aute irure dolor in reprehenderit in voluptate velit esse cillum dolore eu fugiat nulla pariatur. Excepteur sint occaecat cupidatat non proident, sunt in culpa qui officia deserunt mollit anim id est laborum.\n"},{"id":9,"href":"/tutorialtest4/proposal02/","title":"案２","parent":"Oracle Cloud Infrastructure チュートリアル","content":"Kind: section\nPath: /proposal02/_index.md\nチュートリアル１ 北村追記 2025/06/10 lerem ipsum dolor sit amet, consectetur adipiscing elit, sed do eiusmod tempor incididunt ut labore et dolore magna aliqua. Ut enim ad minim veniam, quis nostrud exercitation ullamco laboris nisi ut aliquip ex ea commodo consequat. Duis aute irure dolor in reprehenderit in voluptate velit esse cillum dolore eu fugiat nulla pariatur. Excepteur sint occaecat cupidatat non proident, sunt in culpa qui officia deserunt mollit anim id est laborum.\nチュートリアル別 lorem ipsum dolor sit amet, consectetur adipiscing elit, sed do eiusmod tempor incididunt ut labore et dolore magna aliqua. Ut enim ad minim veniam, quis nostrud exercitation ullamco laboris nisi ut aliquip ex ea commodo consequat. Duis aute irure dolor in reprehenderit in voluptate velit esse cillum dolore eu fugiat nulla pariatur. Excepteur sint occaecat cupidatat non proident, sunt in culpa qui officia deserunt mollit anim id est laborum.\n","description":"Kind: section\nPath: /proposal02/_index.md\nチュートリアル１ 北村追記 2025/06/10 lerem ipsum dolor sit amet, consectetur adipiscing elit, sed do eiusmod tempor incididunt ut labore et dolore magna aliqua. Ut enim ad minim veniam, quis nostrud exercitation ullamco laboris nisi ut aliquip ex ea commodo consequat. Duis aute irure dolor in reprehenderit in voluptate velit esse cillum dolore eu fugiat nulla pariatur. Excepteur sint occaecat cupidatat non proident, sunt in culpa qui officia deserunt mollit anim id est laborum.\n"},{"id":10,"href":"/tutorialtest4/tags/%E5%88%9D%E5%BF%83%E8%80%85/","title":"初心者","parent":"Tags","content":"","description":""}]